starwhisper_observation_calculator/__init__.py
starwhisper_observation_calculator/__main__.py
starwhisper_observation_calculator/cli.py
starwhisper_observation_calculator/core.py
starwhisper_observation_calculator/mcp_server.py
starwhisper_observation_calculator/py.typed
starwhisper_observation_calculator/web_server.py
starwhisper_observability_calc-1.0.3.dist-info/LICENSE
starwhisper_observability_calc-1.0.3.dist-info/METADATA
starwhisper_observability_calc-1.0.3.dist-info/WHEEL
starwhisper_observability_calc-1.0.3.dist-info/entry_points.txt
starwhisper_observability_calc-1.0.3.dist-info/top_level.txt
starwhisper_observability_calc-1.0.3.dist-info/RECORD
