Metadata-Version: 2.1
Name: starwhisper-observability-calc
Version: 1.0.3
Summary: 天文可观测性计算器 - 支持恒星、深空天体和太阳系天体的可观测性计算，提供MCP和Web服务
Author-email: Cunshi Wang <wangcunshi@nao.cas.cn>
Maintainer-email: Cunshi Wang <wangcunshi@nao.cas.cn>
License: MIT
Project-URL: Homepage, https://github.com/wangcunshi/StarWhisper-observation-calculator
Project-URL: Repository, https://github.com/wangcunshi/StarWhisper-observation-calculator
Project-URL: Documentation, https://github.com/wangcunshi/StarWhisper-observation-calculator#readme
Project-URL: Issues, https://github.com/wangcunshi/StarWhisper-observation-calculator/issues
Project-URL: Changelog, https://github.com/wangcunshi/StarWhisper-observation-calculator/blob/main/CHANGELOG.md
Project-URL: Download, https://pypi.org/project/starwhisper-observability-calc/
Keywords: astronomy,observability,mcp,model-context-protocol,astropy,simbad,starwhisper,observatory,calculation,uvx,fastmcp
Classifier: Development Status :: 4 - Beta
Classifier: Intended Audience :: Science/Research
Classifier: Intended Audience :: Developers
Classifier: License :: OSI Approved :: MIT License
Classifier: Operating System :: OS Independent
Classifier: Programming Language :: Python :: 3
Classifier: Programming Language :: Python :: 3.8
Classifier: Programming Language :: Python :: 3.9
Classifier: Programming Language :: Python :: 3.10
Classifier: Programming Language :: Python :: 3.11
Classifier: Programming Language :: Python :: 3.12
Classifier: Topic :: Scientific/Engineering :: Astronomy
Classifier: Topic :: Scientific/Engineering :: Physics
Classifier: Topic :: Software Development :: Libraries :: Python Modules
Classifier: Environment :: Console
Classifier: Framework :: FastAPI
Classifier: Typing :: Typed
Requires-Python: >=3.8
License-File: LICENSE
Requires-Dist: astropy >=5.0.0
Requires-Dist: astroquery >=0.4.6
Requires-Dist: astroplan >=0.8.0
Requires-Dist: numpy >=1.20.0
Requires-Dist: typing-extensions >=4.0.0
Provides-Extra: all
Requires-Dist: starwhisper-observability-calc[web] ; extra == 'all'
Requires-Dist: starwhisper-observability-calc[dev] ; extra == 'all'
Provides-Extra: dev
Requires-Dist: pytest >=6.0.0 ; extra == 'dev'
Requires-Dist: pytest-cov >=3.0.0 ; extra == 'dev'
Requires-Dist: black >=22.0.0 ; extra == 'dev'
Requires-Dist: isort >=5.0.0 ; extra == 'dev'
Requires-Dist: flake8 >=4.0.0 ; extra == 'dev'
Requires-Dist: mypy >=0.910 ; extra == 'dev'
Requires-Dist: pre-commit >=2.15.0 ; extra == 'dev'
Requires-Dist: build >=0.10.0 ; extra == 'dev'
Requires-Dist: twine >=4.0.0 ; extra == 'dev'
Provides-Extra: web
Requires-Dist: fastapi >=0.104.0 ; extra == 'web'
Requires-Dist: uvicorn[standard] >=0.24.0 ; extra == 'web'
Requires-Dist: pydantic >=2.0.0 ; extra == 'web'
